hottbox/__init__.py
hottbox/utils.py
hottbox/version.py
hottbox/algorithms/__init__.py
hottbox/algorithms/classification/__init__.py
hottbox/algorithms/classification/base.py
hottbox/algorithms/classification/ensemble_learning.py
hottbox/algorithms/classification/stm.py
hottbox/algorithms/classification/tests/__init__.py
hottbox/algorithms/classification/tests/test_base.py
hottbox/algorithms/classification/tests/test_ensemble_learning.py
hottbox/algorithms/classification/tests/test_stm.py
hottbox/algorithms/decomposition/__init__.py
hottbox/algorithms/decomposition/base.py
hottbox/algorithms/decomposition/cpd.py
hottbox/algorithms/decomposition/tensor_train.py
hottbox/algorithms/decomposition/tucker.py
hottbox/algorithms/decomposition/fusion/__init__.py
hottbox/algorithms/decomposition/fusion/cmtf.py
hottbox/algorithms/decomposition/fusion/tests/__init__.py
hottbox/algorithms/decomposition/fusion/tests/test_cmtf.py
hottbox/algorithms/decomposition/tests/__init__.py
hottbox/algorithms/decomposition/tests/test_base.py
hottbox/algorithms/decomposition/tests/test_cpd.py
hottbox/algorithms/decomposition/tests/test_tensor_train.py
hottbox/algorithms/decomposition/tests/test_tucker.py
hottbox/contrib/__init__.py
hottbox/contrib/visualisation/__init__.py
hottbox/core/__init__.py
hottbox/core/_meta.py
hottbox/core/operations.py
hottbox/core/structures.py
hottbox/core/tests/__init__.py
hottbox/core/tests/test_meta.py
hottbox/core/tests/test_operations.py
hottbox/core/tests/test_structures.py
hottbox/datasets/__init__.py
hottbox/datasets/synthetic.py
hottbox/datasets/tests/__init__.py
hottbox/datasets/tests/test_synthetic.py
hottbox/errors/__init__.py
hottbox/metrics/__init__.py
hottbox/metrics/base.py
hottbox/metrics/classification.py
hottbox/metrics/decomposition.py
hottbox/metrics/tests/__init__.py
hottbox/metrics/tests/test_base.py
hottbox/metrics/tests/test_decomposition.py
hottbox/pdtools/__init__.py
hottbox/pdtools/utils.py
hottbox/pdtools/tests/__init__.py
hottbox-0.3.2.dist-info/AUTHORS.rst
hottbox-0.3.2.dist-info/LICENSE
hottbox-0.3.2.dist-info/METADATA
hottbox-0.3.2.dist-info/WHEEL
hottbox-0.3.2.dist-info/top_level.txt
hottbox-0.3.2.dist-info/RECORD
