Metadata-Version: 2.1
Name: hottbox
Version: 0.3.2
Summary: Higher Order Tensors ToolBOX
Home-page: https://github.com/hottbox/hottbox
Author: Ilya Kisil
Author-email: ilyakisil@gmail.com
License: Apache License 2.0
Keywords: tensor decompositions,machine learning
Platform: UNKNOWN
Classifier: Development Status :: 3 - Alpha
Classifier: Topic :: Scientific/Engineering
Classifier: Intended Audience :: Developers
Classifier: Intended Audience :: Education
Classifier: Intended Audience :: Science/Research
Classifier: License :: OSI Approved :: Apache Software License
Classifier: Programming Language :: Python :: 3
Requires-Python: >=3.6
Requires-Dist: numpy
Requires-Dist: scipy
Requires-Dist: pandas
Requires-Dist: scikit-learn
Provides-Extra: all
Requires-Dist: pytest (>=5.0.0) ; extra == 'all'
Requires-Dist: pytest-cov (>=2.7.1) ; extra == 'all'
Requires-Dist: sphinx (>=2.1.2) ; extra == 'all'
Requires-Dist: guzzle-sphinx-theme (==0.7.11) ; extra == 'all'
Requires-Dist: numpydoc (==0.9.1) ; extra == 'all'
Requires-Dist: m2r (>=0.2.1) ; extra == 'all'
Provides-Extra: docs
Requires-Dist: sphinx (>=2.1.2) ; extra == 'docs'
Requires-Dist: guzzle-sphinx-theme (==0.7.11) ; extra == 'docs'
Requires-Dist: numpydoc (==0.9.1) ; extra == 'docs'
Requires-Dist: m2r (>=0.2.1) ; extra == 'docs'
Provides-Extra: tests
Requires-Dist: pytest (>=5.0.0) ; extra == 'tests'
Requires-Dist: pytest-cov (>=2.7.1) ; extra == 'tests'
